Fetch
contact_info
nutsFetchGet
nutsOrganizationMethods
nutsPUTupdate
nutsSendPost
nutsVendorMethods
organizationDetails
vendorDetails
