Metadata-Version: 2.1
Name: classe
Version: 1.0.4
Summary: Classes for scripts
Author: Bogdan Marcu
Author-email: bogdan.marcu@tss-yonder.com
